reconfillion/__init__.py
reconfillion/reconf.py
reconfillion-1.0.1.dist-info/LICENSE.txt
reconfillion-1.0.1.dist-info/METADATA
reconfillion-1.0.1.dist-info/WHEEL
reconfillion-1.0.1.dist-info/top_level.txt
reconfillion-1.0.1.dist-info/RECORD
