Metadata-Version: 2.1
Name: reconfillion
Version: 1.0.1
Summary: Solving combinatorial reconfiguration problems.
Author-email: Jun Kawahara <junkawahara@users.noreply.github.com>
License: License
Project-URL: Homepage, https://github.com/junkawahara/reconfillion
Keywords: graph algorithm,combinatorial reconfiguration,graphillion
License-File: LICENSE.txt
Requires-Dist: graphillion >=1.7
